drf_helpers/__init__.py
drf_helpers/action_maps.py
drf_helpers/filters.py
drf_helpers/metadata.py
drf_helpers/mixins.py
drf_helpers/negotiators.py
drf_helpers/pagination.py
drf_helpers/permissions.py
drf_helpers/routers.py
drf_helpers/routes.py
drf_helpers/serializers.py
drf_helpers/urls.py
drf_helpers/views.py
drf_helpers/viewsets.py
rest_framework_helpers/__init__.py
rest_framework_helpers/action_maps.py
rest_framework_helpers/fields.py
rest_framework_helpers/filters.py
rest_framework_helpers/metadata.py
rest_framework_helpers/mixins.py
rest_framework_helpers/negotiators.py
rest_framework_helpers/pagination.py
rest_framework_helpers/permissions.py
rest_framework_helpers/routers.py
rest_framework_helpers/routes.py
rest_framework_helpers/serializers.py
rest_framework_helpers/urls.py
rest_framework_helpers/utils.py
rest_framework_helpers/views.py
rest_framework_helpers/viewsets.py
rest_framework_helpers/expandable/__init__.py
rest_framework_helpers/expandable/fields.py
rest_framework_helpers/expandable/mixins.py
rest_framework_helpers/expandable/serializers.py
django_rest_framework_helpers-8.5.0.dist-info/LICENSE.txt
django_rest_framework_helpers-8.5.0.dist-info/METADATA
django_rest_framework_helpers-8.5.0.dist-info/WHEEL
django_rest_framework_helpers-8.5.0.dist-info/top_level.txt
django_rest_framework_helpers-8.5.0.dist-info/RECORD
